Metadata-Version: 1.0
Name: dsnd-probability-beta-001
Version: 0.1
Summary: Gaussian and Binomial Distribution
Home-page: UNKNOWN
Author: UNKNOWN
Author-email: UNKNOWN
License: UNKNOWN
Platform: UNKNOWN
